sintt2.py
sintt2-2.0.0.dist-info/METADATA
sintt2-2.0.0.dist-info/WHEEL
sintt2-2.0.0.dist-info/top_level.txt
sintt2-2.0.0.dist-info/RECORD
