Metadata-Version: 2.1
Name: sintt2
Version: 2.0.0
Summary: makes life easier
Author: SINTT
Author-email: bbhh66606@gmail.com
Requires-Dist: pyodbc
Requires-Dist: Pillow
